{
	"name": "Iqro12_Eventsheet",
	"events": [
		{
			"eventType": "variable",
			"name": "Iqro12",
			"type": "number",
			"initialValue": "0",
			"comment": "",
			"isStatic": false,
			"isConstant": false,
			"sid": 467417066334401
		},
		{
			"eventType": "group",
			"disabled": false,
			"title": "ON START LAYOUT IQRO12",
			"description": "",
			"isActiveOnStart": true,
			"children": [
				{
					"eventType": "block",
					"conditions": [
						{
							"id": "on-start-of-layout",
							"objectClass": "System",
							"sid": 784362618849547
						}
					],
					"actions": [
						{
							"id": "set-instvar-value",
							"objectClass": "btnKembali",
							"sid": 400653400734423,
							"parameters": {
								"instance-variable": "UkuranX",
								"value": "Self.Width"
							}
						},
						{
							"id": "set-instvar-value",
							"objectClass": "btnKembali",
							"sid": 180398301959951,
							"parameters": {
								"instance-variable": "UkuranY",
								"value": "Self.Height"
							}
						},
						{
							"id": "set-instvar-value",
							"objectClass": "btnSelanjutnya",
							"sid": 694392330780802,
							"parameters": {
								"instance-variable": "UkuranX",
								"value": "Self.Width"
							}
						},
						{
							"id": "set-instvar-value",
							"objectClass": "btnSelanjutnya",
							"sid": 458896160333839,
							"parameters": {
								"instance-variable": "UkuranY",
								"value": "Self.Height"
							}
						},
						{
							"id": "set-instvar-value",
							"objectClass": "btnMateri_sifat",
							"sid": 610112969043018,
							"parameters": {
								"instance-variable": "UkuranX",
								"value": "Self.Width"
							}
						},
						{
							"id": "set-instvar-value",
							"objectClass": "btnMateri_sifat",
							"sid": 244231855592553,
							"parameters": {
								"instance-variable": "UkuranY",
								"value": "Self.Height"
							}
						},
						{
							"id": "set-instvar-value",
							"objectClass": "btnMenu",
							"sid": 281142970590364,
							"parameters": {
								"instance-variable": "UkuranX",
								"value": "Self.Width"
							}
						},
						{
							"id": "set-instvar-value",
							"objectClass": "btnMenu",
							"sid": 412414277086873,
							"parameters": {
								"instance-variable": "UkuranY",
								"value": "Self.Height"
							}
						},
						{
							"id": "set-instvar-value",
							"objectClass": "btnKeluar",
							"sid": 170112858750831,
							"parameters": {
								"instance-variable": "UkuranX",
								"value": "Self.Width"
							}
						},
						{
							"id": "set-instvar-value",
							"objectClass": "btnKeluar",
							"sid": 526956188946849,
							"parameters": {
								"instance-variable": "UkuranY",
								"value": "Self.Height"
							}
						},
						{
							"id": "set-instvar-value",
							"objectClass": "12a",
							"sid": 310655920192517,
							"parameters": {
								"instance-variable": "AyatX",
								"value": "Self.Width"
							}
						},
						{
							"id": "set-instvar-value",
							"objectClass": "12a",
							"sid": 609316436315916,
							"parameters": {
								"instance-variable": "AyatY",
								"value": "Self.Height"
							}
						},
						{
							"id": "reset-global-variables",
							"objectClass": "System",
							"sid": 388421611773726
						},
						{
							"id": "play",
							"objectClass": "Audio",
							"sid": 909910355961556,
							"parameters": {
								"audio-file": "Materi7",
								"loop": "not-looping",
								"volume": "0",
								"stereo-pan": "0",
								"tag-optional": "\"\""
							}
						}
					],
					"sid": 371269489846874
				}
			],
			"sid": 412107633463195
		},
		{
			"eventType": "group",
			"disabled": false,
			"title": "SizeLayout IQRO12",
			"description": "",
			"isActiveOnStart": true,
			"children": [
				{
					"eventType": "block",
					"conditions": [
						{
							"id": "is-touching-object",
							"objectClass": "Touch",
							"sid": 743068956533266,
							"parameters": {
								"object": "btnKembali"
							}
						}
					],
					"actions": [],
					"sid": 718392520544118,
					"children": [
						{
							"eventType": "block",
							"conditions": [
								{
									"id": "on-any-touch-end",
									"objectClass": "Touch",
									"sid": 986185868941806
								}
							],
							"actions": [
								{
									"id": "go-to-layout",
									"objectClass": "System",
									"sid": 393321664385793,
									"parameters": {
										"layout": "Iqro_11"
									}
								}
							],
							"sid": 491348924019796
						}
					]
				},
				{
					"eventType": "block",
					"conditions": [
						{
							"id": "is-touching-object",
							"objectClass": "Touch",
							"sid": 706557855474774,
							"parameters": {
								"object": "btnSelanjutnya"
							}
						}
					],
					"actions": [],
					"sid": 536214007856553,
					"children": [
						{
							"eventType": "block",
							"conditions": [
								{
									"id": "on-any-touch-end",
									"objectClass": "Touch",
									"sid": 794108934809462
								}
							],
							"actions": [
								{
									"id": "go-to-layout",
									"objectClass": "System",
									"sid": 790729941508447,
									"parameters": {
										"layout": "Iqro_13"
									}
								}
							],
							"sid": 339956494909125
						}
					]
				},
				{
					"eventType": "block",
					"conditions": [
						{
							"id": "is-touching-object",
							"objectClass": "Touch",
							"sid": 520346657731971,
							"parameters": {
								"object": "btnMenu"
							}
						}
					],
					"actions": [],
					"sid": 367821740741121,
					"children": [
						{
							"eventType": "block",
							"conditions": [
								{
									"id": "on-any-touch-end",
									"objectClass": "Touch",
									"sid": 481271161569305
								}
							],
							"actions": [
								{
									"id": "go-to-layout",
									"objectClass": "System",
									"sid": 350932715258748,
									"parameters": {
										"layout": "MenuIQRO"
									}
								}
							],
							"sid": 540819391554225
						}
					]
				},
				{
					"eventType": "block",
					"conditions": [
						{
							"id": "on-touched-object",
							"objectClass": "Touch",
							"sid": 566443741760509,
							"parameters": {
								"object": "btnMenu",
								"type": "start"
							}
						}
					],
					"actions": [
						{
							"id": "stop-all",
							"objectClass": "Audio",
							"sid": 217734516515122
						},
						{
							"id": "tween-two-properties",
							"objectClass": "btnMenu",
							"sid": 280469441970127,
							"behaviorType": "Tween",
							"parameters": {
								"tags": "\"\"",
								"property": "size",
								"end-x": "Self.UkuranX+50",
								"end-y": "Self.UkuranY+50",
								"time": "0.2",
								"ease": "easeoutback",
								"destroy-on-complete": "no",
								"loop": "no",
								"ping-pong": "no",
								"repeat-count": "1"
							}
						},
						{
							"id": "wait",
							"objectClass": "System",
							"sid": 382355344127499,
							"parameters": {
								"seconds": "0.2"
							}
						},
						{
							"id": "tween-two-properties",
							"objectClass": "btnMenu",
							"sid": 758298703151019,
							"behaviorType": "Tween",
							"parameters": {
								"tags": "\"\"",
								"property": "size",
								"end-x": "Self.UkuranX",
								"end-y": "Self.UkuranY",
								"time": "0.2",
								"ease": "easeinback",
								"destroy-on-complete": "no",
								"loop": "no",
								"ping-pong": "no",
								"repeat-count": "1"
							}
						}
					],
					"sid": 539139995241894
				},
				{
					"eventType": "block",
					"conditions": [
						{
							"id": "on-touched-object",
							"objectClass": "Touch",
							"sid": 830344220347059,
							"parameters": {
								"object": "btnKembali",
								"type": "start"
							}
						}
					],
					"actions": [
						{
							"id": "stop-all",
							"objectClass": "Audio",
							"sid": 557072019841630
						},
						{
							"id": "tween-two-properties",
							"objectClass": "btnKembali",
							"sid": 194480026695399,
							"behaviorType": "Tween",
							"parameters": {
								"tags": "\"\"",
								"property": "size",
								"end-x": "Self.UkuranX+50",
								"end-y": "Self.UkuranY+50",
								"time": "0.2",
								"ease": "easeoutback",
								"destroy-on-complete": "no",
								"loop": "no",
								"ping-pong": "no",
								"repeat-count": "1"
							}
						},
						{
							"id": "wait",
							"objectClass": "System",
							"sid": 857325666297052,
							"parameters": {
								"seconds": "0.2"
							}
						},
						{
							"id": "tween-two-properties",
							"objectClass": "btnKembali",
							"sid": 979362235084069,
							"behaviorType": "Tween",
							"parameters": {
								"tags": "\"\"",
								"property": "size",
								"end-x": "Self.UkuranX",
								"end-y": "Self.UkuranY",
								"time": "0.2",
								"ease": "easeinback",
								"destroy-on-complete": "no",
								"loop": "no",
								"ping-pong": "no",
								"repeat-count": "1"
							}
						}
					],
					"sid": 874333790733964
				},
				{
					"eventType": "block",
					"conditions": [
						{
							"id": "on-touched-object",
							"objectClass": "Touch",
							"sid": 200672121496072,
							"parameters": {
								"object": "btnSelanjutnya",
								"type": "start"
							}
						}
					],
					"actions": [
						{
							"id": "stop-all",
							"objectClass": "Audio",
							"sid": 684019408989704
						},
						{
							"id": "tween-two-properties",
							"objectClass": "btnSelanjutnya",
							"sid": 203300481990826,
							"behaviorType": "Tween",
							"parameters": {
								"tags": "\"\"",
								"property": "size",
								"end-x": "Self.UkuranX+50",
								"end-y": "Self.UkuranY+50",
								"time": "0.2",
								"ease": "easeoutback",
								"destroy-on-complete": "no",
								"loop": "no",
								"ping-pong": "no",
								"repeat-count": "1"
							}
						},
						{
							"id": "wait",
							"objectClass": "System",
							"sid": 132117810165412,
							"parameters": {
								"seconds": "0.2"
							}
						},
						{
							"id": "tween-two-properties",
							"objectClass": "btnSelanjutnya",
							"sid": 240330729908436,
							"behaviorType": "Tween",
							"parameters": {
								"tags": "\"\"",
								"property": "size",
								"end-x": "Self.UkuranX",
								"end-y": "Self.UkuranY",
								"time": "0.2",
								"ease": "easeinback",
								"destroy-on-complete": "no",
								"loop": "no",
								"ping-pong": "no",
								"repeat-count": "1"
							}
						}
					],
					"sid": 519132969478224
				},
				{
					"eventType": "block",
					"conditions": [
						{
							"id": "is-touching-object",
							"objectClass": "Touch",
							"sid": 752552077728683,
							"parameters": {
								"object": "btnKeluar"
							}
						}
					],
					"actions": [],
					"sid": 104217948277616,
					"children": [
						{
							"eventType": "block",
							"conditions": [
								{
									"id": "on-any-touch-end",
									"objectClass": "Touch",
									"sid": 858053983801672
								}
							],
							"actions": [
								{
									"id": "go-to-layout",
									"objectClass": "System",
									"sid": 108900961437141,
									"parameters": {
										"layout": "BelajarYuk"
									}
								}
							],
							"sid": 968954087013797
						}
					]
				},
				{
					"eventType": "block",
					"conditions": [
						{
							"id": "on-touched-object",
							"objectClass": "Touch",
							"sid": 174779575332979,
							"parameters": {
								"object": "btnKeluar",
								"type": "start"
							}
						}
					],
					"actions": [
						{
							"id": "stop-all",
							"objectClass": "Audio",
							"sid": 128896515435089
						},
						{
							"id": "tween-two-properties",
							"objectClass": "btnKeluar",
							"sid": 881485342644777,
							"behaviorType": "Tween",
							"parameters": {
								"tags": "\"\"",
								"property": "size",
								"end-x": "Self.UkuranX+50",
								"end-y": "Self.UkuranY+50",
								"time": "0.2",
								"ease": "easeoutback",
								"destroy-on-complete": "no",
								"loop": "no",
								"ping-pong": "no",
								"repeat-count": "1"
							}
						},
						{
							"id": "wait",
							"objectClass": "System",
							"sid": 839350786482553,
							"parameters": {
								"seconds": "0.2"
							}
						},
						{
							"id": "tween-two-properties",
							"objectClass": "btnKeluar",
							"sid": 120880712723552,
							"behaviorType": "Tween",
							"parameters": {
								"tags": "\"\"",
								"property": "size",
								"end-x": "Self.UkuranX",
								"end-y": "Self.UkuranY",
								"time": "0.2",
								"ease": "easeinback",
								"destroy-on-complete": "no",
								"loop": "no",
								"ping-pong": "no",
								"repeat-count": "1"
							}
						}
					],
					"sid": 984114336429773
				},
				{
					"eventType": "block",
					"conditions": [
						{
							"id": "on-touched-object",
							"objectClass": "Touch",
							"sid": 711511903822735,
							"parameters": {
								"object": "btnMateri_sifat",
								"type": "start"
							}
						}
					],
					"actions": [],
					"sid": 584583663739250,
					"children": [
						{
							"eventType": "block",
							"conditions": [
								{
									"id": "compare-animation-frame",
									"objectClass": "btnMateri_sifat",
									"sid": 969027695581948,
									"parameters": {
										"comparison": 0,
										"number": "1"
									}
								}
							],
							"actions": [
								{
									"id": "play",
									"objectClass": "Audio",
									"sid": 342455947264980,
									"parameters": {
										"audio-file": "Materi7",
										"loop": "not-looping",
										"volume": "0",
										"stereo-pan": "0",
										"tag-optional": "\"\""
									}
								},
								{
									"id": "set-animation-frame",
									"objectClass": "btnMateri_sifat",
									"sid": 473587844875500,
									"parameters": {
										"frame-number": "2"
									}
								},
								{
									"id": "wait",
									"objectClass": "System",
									"sid": 438723237671922,
									"parameters": {
										"seconds": "9"
									}
								},
								{
									"id": "set-animation-frame",
									"objectClass": "btnMateri_sifat",
									"sid": 595177668367439,
									"parameters": {
										"frame-number": "1"
									}
								}
							],
							"sid": 131877159457081
						},
						{
							"eventType": "block",
							"conditions": [
								{
									"id": "else",
									"objectClass": "System",
									"sid": 613088727375663
								}
							],
							"actions": [
								{
									"id": "stop-all",
									"objectClass": "Audio",
									"sid": 673979526485860
								},
								{
									"id": "set-animation-frame",
									"objectClass": "btnMateri_sifat",
									"sid": 233274358174878,
									"parameters": {
										"frame-number": "1"
									}
								}
							],
							"sid": 899041166926071
						}
					]
				}
			],
			"sid": 251927979606690
		},
		{
			"eventType": "group",
			"disabled": false,
			"title": "FunctionLayout IQRO12",
			"description": "",
			"isActiveOnStart": true,
			"children": [
				{
					"functionName": "Iqro12",
					"functionDescription": "",
					"functionCategory": "",
					"functionReturnType": "none",
					"functionCopyPicked": false,
					"functionIsAsync": false,
					"functionParameters": [],
					"eventType": "function-block",
					"conditions": [],
					"actions": [],
					"sid": 518491487383155,
					"children": [
						{
							"eventType": "block",
							"conditions": [
								{
									"id": "compare-eventvar",
									"objectClass": "System",
									"sid": 377893168884974,
									"parameters": {
										"variable": "Iqro12",
										"comparison": 0,
										"value": "1"
									}
								},
								{
									"id": "compare-animation-frame",
									"objectClass": "12a",
									"sid": 707914204767040,
									"parameters": {
										"comparison": 0,
										"number": "1"
									}
								}
							],
							"actions": [
								{
									"id": "stop-all",
									"objectClass": "Audio",
									"sid": 565842986213272
								},
								{
									"id": "play",
									"objectClass": "Audio",
									"sid": 875793747367540,
									"parameters": {
										"audio-file": "1L",
										"loop": "not-looping",
										"volume": "0",
										"stereo-pan": "0",
										"tag-optional": "\"\""
									}
								},
								{
									"id": "tween-two-properties",
									"objectClass": "12a",
									"sid": 944534465396053,
									"behaviorType": "Tween",
									"parameters": {
										"tags": "\"\"",
										"property": "size",
										"end-x": "Self.AyatX+50",
										"end-y": "Self.AyatY+50",
										"time": "0.2",
										"ease": "default",
										"destroy-on-complete": "no",
										"loop": "no",
										"ping-pong": "no",
										"repeat-count": "1"
									}
								},
								{
									"id": "set-animation-frame",
									"objectClass": "12a",
									"sid": 617655818027476,
									"parameters": {
										"frame-number": "16"
									}
								},
								{
									"id": "wait",
									"objectClass": "System",
									"sid": 515247929169894,
									"parameters": {
										"seconds": "3"
									}
								},
								{
									"id": "set-animation-frame",
									"objectClass": "12a",
									"sid": 112891832949312,
									"parameters": {
										"frame-number": "1"
									}
								},
								{
									"id": "tween-two-properties",
									"objectClass": "12a",
									"sid": 655342616084518,
									"behaviorType": "Tween",
									"parameters": {
										"tags": "\"\"",
										"property": "size",
										"end-x": "Self.AyatX",
										"end-y": "Self.AyatY",
										"time": "0.2",
										"ease": "easeinback",
										"destroy-on-complete": "no",
										"loop": "no",
										"ping-pong": "no",
										"repeat-count": "1"
									}
								}
							],
							"sid": 573227289684476
						},
						{
							"eventType": "block",
							"conditions": [
								{
									"id": "compare-eventvar",
									"objectClass": "System",
									"sid": 623198213075164,
									"parameters": {
										"variable": "Iqro12",
										"comparison": 0,
										"value": "2"
									}
								},
								{
									"id": "compare-animation-frame",
									"objectClass": "12a",
									"sid": 557419226760775,
									"parameters": {
										"comparison": 0,
										"number": "2"
									}
								}
							],
							"actions": [
								{
									"id": "stop-all",
									"objectClass": "Audio",
									"sid": 296051977728552
								},
								{
									"id": "play",
									"objectClass": "Audio",
									"sid": 644400178570666,
									"parameters": {
										"audio-file": "2L",
										"loop": "not-looping",
										"volume": "0",
										"stereo-pan": "0",
										"tag-optional": "\"\""
									}
								},
								{
									"id": "tween-two-properties",
									"objectClass": "12a",
									"sid": 381825754372789,
									"behaviorType": "Tween",
									"parameters": {
										"tags": "\"\"",
										"property": "size",
										"end-x": "Self.AyatX+50",
										"end-y": "Self.AyatY+50",
										"time": "0.2",
										"ease": "default",
										"destroy-on-complete": "no",
										"loop": "no",
										"ping-pong": "no",
										"repeat-count": "1"
									}
								},
								{
									"id": "set-animation-frame",
									"objectClass": "12a",
									"sid": 828867126231759,
									"parameters": {
										"frame-number": "17"
									}
								},
								{
									"id": "wait",
									"objectClass": "System",
									"sid": 496094444701334,
									"parameters": {
										"seconds": "3"
									}
								},
								{
									"id": "set-animation-frame",
									"objectClass": "12a",
									"sid": 553638120125459,
									"parameters": {
										"frame-number": "2"
									}
								},
								{
									"id": "tween-two-properties",
									"objectClass": "12a",
									"sid": 641923008497468,
									"behaviorType": "Tween",
									"parameters": {
										"tags": "\"\"",
										"property": "size",
										"end-x": "Self.AyatX",
										"end-y": "Self.AyatY",
										"time": "0.2",
										"ease": "easeinback",
										"destroy-on-complete": "no",
										"loop": "no",
										"ping-pong": "no",
										"repeat-count": "1"
									}
								}
							],
							"sid": 785073535851748
						},
						{
							"eventType": "block",
							"conditions": [
								{
									"id": "compare-eventvar",
									"objectClass": "System",
									"sid": 204676071360583,
									"parameters": {
										"variable": "Iqro12",
										"comparison": 0,
										"value": "3"
									}
								},
								{
									"id": "compare-animation-frame",
									"objectClass": "12a",
									"sid": 709857794671725,
									"parameters": {
										"comparison": 0,
										"number": "3"
									}
								}
							],
							"actions": [
								{
									"id": "stop-all",
									"objectClass": "Audio",
									"sid": 351687544839553
								},
								{
									"id": "play",
									"objectClass": "Audio",
									"sid": 855286187703281,
									"parameters": {
										"audio-file": "3L",
										"loop": "not-looping",
										"volume": "0",
										"stereo-pan": "0",
										"tag-optional": "\"\""
									}
								},
								{
									"id": "tween-two-properties",
									"objectClass": "12a",
									"sid": 548793597172195,
									"behaviorType": "Tween",
									"parameters": {
										"tags": "\"\"",
										"property": "size",
										"end-x": "Self.AyatX+50",
										"end-y": "Self.AyatY+50",
										"time": "0.2",
										"ease": "default",
										"destroy-on-complete": "no",
										"loop": "no",
										"ping-pong": "no",
										"repeat-count": "1"
									}
								},
								{
									"id": "set-animation-frame",
									"objectClass": "12a",
									"sid": 248986419484819,
									"parameters": {
										"frame-number": "18"
									}
								},
								{
									"id": "wait",
									"objectClass": "System",
									"sid": 960549830129275,
									"parameters": {
										"seconds": "6"
									}
								},
								{
									"id": "set-animation-frame",
									"objectClass": "12a",
									"sid": 122042682293156,
									"parameters": {
										"frame-number": "3"
									}
								},
								{
									"id": "tween-two-properties",
									"objectClass": "12a",
									"sid": 723040695812209,
									"behaviorType": "Tween",
									"parameters": {
										"tags": "\"\"",
										"property": "size",
										"end-x": "Self.AyatX",
										"end-y": "Self.AyatY",
										"time": "0.2",
										"ease": "easeinback",
										"destroy-on-complete": "no",
										"loop": "no",
										"ping-pong": "no",
										"repeat-count": "1"
									}
								}
							],
							"sid": 740075959820497
						},
						{
							"eventType": "block",
							"conditions": [
								{
									"id": "compare-eventvar",
									"objectClass": "System",
									"sid": 209835426145747,
									"parameters": {
										"variable": "Iqro12",
										"comparison": 0,
										"value": "4"
									}
								},
								{
									"id": "compare-animation-frame",
									"objectClass": "12a",
									"sid": 665156724450524,
									"parameters": {
										"comparison": 0,
										"number": "4"
									}
								}
							],
							"actions": [
								{
									"id": "stop-all",
									"objectClass": "Audio",
									"sid": 970123773829697
								},
								{
									"id": "play",
									"objectClass": "Audio",
									"sid": 515963953072190,
									"parameters": {
										"audio-file": "4L",
										"loop": "not-looping",
										"volume": "0",
										"stereo-pan": "0",
										"tag-optional": "\"\""
									}
								},
								{
									"id": "tween-two-properties",
									"objectClass": "12a",
									"sid": 973655568024631,
									"behaviorType": "Tween",
									"parameters": {
										"tags": "\"\"",
										"property": "size",
										"end-x": "Self.AyatX+50",
										"end-y": "Self.AyatY+50",
										"time": "0.2",
										"ease": "default",
										"destroy-on-complete": "no",
										"loop": "no",
										"ping-pong": "no",
										"repeat-count": "1"
									}
								},
								{
									"id": "set-animation-frame",
									"objectClass": "12a",
									"sid": 950669982420746,
									"parameters": {
										"frame-number": "19"
									}
								},
								{
									"id": "wait",
									"objectClass": "System",
									"sid": 372634780852947,
									"parameters": {
										"seconds": "7"
									}
								},
								{
									"id": "set-animation-frame",
									"objectClass": "12a",
									"sid": 817323586263047,
									"parameters": {
										"frame-number": "4"
									}
								},
								{
									"id": "tween-two-properties",
									"objectClass": "12a",
									"sid": 502776864676322,
									"behaviorType": "Tween",
									"parameters": {
										"tags": "\"\"",
										"property": "size",
										"end-x": "Self.AyatX",
										"end-y": "Self.AyatY",
										"time": "0.2",
										"ease": "easeinback",
										"destroy-on-complete": "no",
										"loop": "no",
										"ping-pong": "no",
										"repeat-count": "1"
									}
								}
							],
							"sid": 449219350584684
						},
						{
							"eventType": "block",
							"conditions": [
								{
									"id": "compare-eventvar",
									"objectClass": "System",
									"sid": 656322247467278,
									"parameters": {
										"variable": "Iqro12",
										"comparison": 0,
										"value": "5"
									}
								},
								{
									"id": "compare-animation-frame",
									"objectClass": "12a",
									"sid": 611767022873397,
									"parameters": {
										"comparison": 0,
										"number": "5"
									}
								}
							],
							"actions": [
								{
									"id": "stop-all",
									"objectClass": "Audio",
									"sid": 755876122082934
								},
								{
									"id": "play",
									"objectClass": "Audio",
									"sid": 313991108593581,
									"parameters": {
										"audio-file": "5L",
										"loop": "not-looping",
										"volume": "0",
										"stereo-pan": "0",
										"tag-optional": "\"\""
									}
								},
								{
									"id": "tween-two-properties",
									"objectClass": "12a",
									"sid": 233882275013781,
									"behaviorType": "Tween",
									"parameters": {
										"tags": "\"\"",
										"property": "size",
										"end-x": "Self.AyatX+50",
										"end-y": "Self.AyatY+50",
										"time": "0.2",
										"ease": "default",
										"destroy-on-complete": "no",
										"loop": "no",
										"ping-pong": "no",
										"repeat-count": "1"
									}
								},
								{
									"id": "set-animation-frame",
									"objectClass": "12a",
									"sid": 764773145258018,
									"parameters": {
										"frame-number": "20"
									}
								},
								{
									"id": "wait",
									"objectClass": "System",
									"sid": 871805179211713,
									"parameters": {
										"seconds": "6"
									}
								},
								{
									"id": "set-animation-frame",
									"objectClass": "12a",
									"sid": 516235809025812,
									"parameters": {
										"frame-number": "5"
									}
								},
								{
									"id": "tween-two-properties",
									"objectClass": "12a",
									"sid": 636710921062001,
									"behaviorType": "Tween",
									"parameters": {
										"tags": "\"\"",
										"property": "size",
										"end-x": "Self.AyatX",
										"end-y": "Self.AyatY",
										"time": "0.2",
										"ease": "easeinback",
										"destroy-on-complete": "no",
										"loop": "no",
										"ping-pong": "no",
										"repeat-count": "1"
									}
								}
							],
							"sid": 280974083969510
						},
						{
							"eventType": "block",
							"conditions": [
								{
									"id": "compare-eventvar",
									"objectClass": "System",
									"sid": 767662934521615,
									"parameters": {
										"variable": "Iqro12",
										"comparison": 0,
										"value": "6"
									}
								},
								{
									"id": "compare-animation-frame",
									"objectClass": "12a",
									"sid": 453624485488237,
									"parameters": {
										"comparison": 0,
										"number": "6"
									}
								}
							],
							"actions": [
								{
									"id": "stop-all",
									"objectClass": "Audio",
									"sid": 613161262092466
								},
								{
									"id": "play",
									"objectClass": "Audio",
									"sid": 250310173445352,
									"parameters": {
										"audio-file": "6L",
										"loop": "not-looping",
										"volume": "0",
										"stereo-pan": "0",
										"tag-optional": "\"\""
									}
								},
								{
									"id": "tween-two-properties",
									"objectClass": "12a",
									"sid": 472397031549516,
									"behaviorType": "Tween",
									"parameters": {
										"tags": "\"\"",
										"property": "size",
										"end-x": "Self.AyatX+50",
										"end-y": "Self.AyatY+50",
										"time": "0.2",
										"ease": "default",
										"destroy-on-complete": "no",
										"loop": "no",
										"ping-pong": "no",
										"repeat-count": "1"
									}
								},
								{
									"id": "set-animation-frame",
									"objectClass": "12a",
									"sid": 707617410632140,
									"parameters": {
										"frame-number": "21"
									}
								},
								{
									"id": "wait",
									"objectClass": "System",
									"sid": 878060512877680,
									"parameters": {
										"seconds": "7"
									}
								},
								{
									"id": "set-animation-frame",
									"objectClass": "12a",
									"sid": 453082499597946,
									"parameters": {
										"frame-number": "6"
									}
								},
								{
									"id": "tween-two-properties",
									"objectClass": "12a",
									"sid": 892760921326571,
									"behaviorType": "Tween",
									"parameters": {
										"tags": "\"\"",
										"property": "size",
										"end-x": "Self.AyatX",
										"end-y": "Self.AyatY",
										"time": "0.2",
										"ease": "easeinback",
										"destroy-on-complete": "no",
										"loop": "no",
										"ping-pong": "no",
										"repeat-count": "1"
									}
								}
							],
							"sid": 800920116002469
						},
						{
							"eventType": "block",
							"conditions": [
								{
									"id": "compare-eventvar",
									"objectClass": "System",
									"sid": 386441343186431,
									"parameters": {
										"variable": "Iqro12",
										"comparison": 0,
										"value": "7"
									}
								},
								{
									"id": "compare-animation-frame",
									"objectClass": "12a",
									"sid": 841331610657150,
									"parameters": {
										"comparison": 0,
										"number": "7"
									}
								}
							],
							"actions": [
								{
									"id": "stop-all",
									"objectClass": "Audio",
									"sid": 555811555597030
								},
								{
									"id": "play",
									"objectClass": "Audio",
									"sid": 135189261546151,
									"parameters": {
										"audio-file": "7L",
										"loop": "not-looping",
										"volume": "0",
										"stereo-pan": "0",
										"tag-optional": "\"\""
									}
								},
								{
									"id": "tween-two-properties",
									"objectClass": "12a",
									"sid": 852974647146974,
									"behaviorType": "Tween",
									"parameters": {
										"tags": "\"\"",
										"property": "size",
										"end-x": "Self.AyatX+50",
										"end-y": "Self.AyatY+50",
										"time": "0.2",
										"ease": "default",
										"destroy-on-complete": "no",
										"loop": "no",
										"ping-pong": "no",
										"repeat-count": "1"
									}
								},
								{
									"id": "set-animation-frame",
									"objectClass": "12a",
									"sid": 873991492825132,
									"parameters": {
										"frame-number": "22"
									}
								},
								{
									"id": "wait",
									"objectClass": "System",
									"sid": 556261221798629,
									"parameters": {
										"seconds": "7"
									}
								},
								{
									"id": "set-animation-frame",
									"objectClass": "12a",
									"sid": 779632167672393,
									"parameters": {
										"frame-number": "7"
									}
								},
								{
									"id": "tween-two-properties",
									"objectClass": "12a",
									"sid": 107173373672100,
									"behaviorType": "Tween",
									"parameters": {
										"tags": "\"\"",
										"property": "size",
										"end-x": "Self.AyatX",
										"end-y": "Self.AyatY",
										"time": "0.2",
										"ease": "easeinback",
										"destroy-on-complete": "no",
										"loop": "no",
										"ping-pong": "no",
										"repeat-count": "1"
									}
								}
							],
							"sid": 173706287019964
						},
						{
							"eventType": "block",
							"conditions": [
								{
									"id": "compare-eventvar",
									"objectClass": "System",
									"sid": 197090091435746,
									"parameters": {
										"variable": "Iqro12",
										"comparison": 0,
										"value": "8"
									}
								},
								{
									"id": "compare-animation-frame",
									"objectClass": "12a",
									"sid": 453890837662706,
									"parameters": {
										"comparison": 0,
										"number": "8"
									}
								}
							],
							"actions": [
								{
									"id": "stop-all",
									"objectClass": "Audio",
									"sid": 565992625435071
								},
								{
									"id": "play",
									"objectClass": "Audio",
									"sid": 169388534362772,
									"parameters": {
										"audio-file": "8L",
										"loop": "not-looping",
										"volume": "0",
										"stereo-pan": "0",
										"tag-optional": "\"\""
									}
								},
								{
									"id": "tween-two-properties",
									"objectClass": "12a",
									"sid": 256404290946578,
									"behaviorType": "Tween",
									"parameters": {
										"tags": "\"\"",
										"property": "size",
										"end-x": "Self.AyatX+50",
										"end-y": "Self.AyatY+50",
										"time": "0.2",
										"ease": "default",
										"destroy-on-complete": "no",
										"loop": "no",
										"ping-pong": "no",
										"repeat-count": "1"
									}
								},
								{
									"id": "set-animation-frame",
									"objectClass": "12a",
									"sid": 931884297623427,
									"parameters": {
										"frame-number": "23"
									}
								},
								{
									"id": "wait",
									"objectClass": "System",
									"sid": 989082693245774,
									"parameters": {
										"seconds": "7"
									}
								},
								{
									"id": "set-animation-frame",
									"objectClass": "12a",
									"sid": 363786646916720,
									"parameters": {
										"frame-number": "8"
									}
								},
								{
									"id": "tween-two-properties",
									"objectClass": "12a",
									"sid": 761074910581915,
									"behaviorType": "Tween",
									"parameters": {
										"tags": "\"\"",
										"property": "size",
										"end-x": "Self.AyatX",
										"end-y": "Self.AyatY",
										"time": "0.2",
										"ease": "easeinback",
										"destroy-on-complete": "no",
										"loop": "no",
										"ping-pong": "no",
										"repeat-count": "1"
									}
								}
							],
							"sid": 578907628640652
						},
						{
							"eventType": "block",
							"conditions": [
								{
									"id": "compare-eventvar",
									"objectClass": "System",
									"sid": 114515489652288,
									"parameters": {
										"variable": "Iqro12",
										"comparison": 0,
										"value": "9"
									}
								},
								{
									"id": "compare-animation-frame",
									"objectClass": "12a",
									"sid": 104339634390006,
									"parameters": {
										"comparison": 0,
										"number": "9"
									}
								}
							],
							"actions": [
								{
									"id": "stop-all",
									"objectClass": "Audio",
									"sid": 780934143780492
								},
								{
									"id": "play",
									"objectClass": "Audio",
									"sid": 711487766784866,
									"parameters": {
										"audio-file": "9L",
										"loop": "not-looping",
										"volume": "0",
										"stereo-pan": "0",
										"tag-optional": "\"\""
									}
								},
								{
									"id": "tween-two-properties",
									"objectClass": "12a",
									"sid": 564340921951353,
									"behaviorType": "Tween",
									"parameters": {
										"tags": "\"\"",
										"property": "size",
										"end-x": "Self.AyatX+50",
										"end-y": "Self.AyatY+50",
										"time": "0.2",
										"ease": "default",
										"destroy-on-complete": "no",
										"loop": "no",
										"ping-pong": "no",
										"repeat-count": "1"
									}
								},
								{
									"id": "set-animation-frame",
									"objectClass": "12a",
									"sid": 562590317967691,
									"parameters": {
										"frame-number": "24"
									}
								},
								{
									"id": "wait",
									"objectClass": "System",
									"sid": 508182029858159,
									"parameters": {
										"seconds": "7"
									}
								},
								{
									"id": "set-animation-frame",
									"objectClass": "12a",
									"sid": 927719856365021,
									"parameters": {
										"frame-number": "9"
									}
								},
								{
									"id": "tween-two-properties",
									"objectClass": "12a",
									"sid": 798757197912222,
									"behaviorType": "Tween",
									"parameters": {
										"tags": "\"\"",
										"property": "size",
										"end-x": "Self.AyatX",
										"end-y": "Self.AyatY",
										"time": "0.2",
										"ease": "easeinback",
										"destroy-on-complete": "no",
										"loop": "no",
										"ping-pong": "no",
										"repeat-count": "1"
									}
								}
							],
							"sid": 746844906815843
						},
						{
							"eventType": "block",
							"conditions": [
								{
									"id": "compare-eventvar",
									"objectClass": "System",
									"sid": 319689800369777,
									"parameters": {
										"variable": "Iqro12",
										"comparison": 0,
										"value": "10"
									}
								},
								{
									"id": "compare-animation-frame",
									"objectClass": "12a",
									"sid": 820928788325780,
									"parameters": {
										"comparison": 0,
										"number": "10"
									}
								}
							],
							"actions": [
								{
									"id": "stop-all",
									"objectClass": "Audio",
									"sid": 897360272068928
								},
								{
									"id": "play",
									"objectClass": "Audio",
									"sid": 807571354562923,
									"parameters": {
										"audio-file": "10L",
										"loop": "not-looping",
										"volume": "0",
										"stereo-pan": "0",
										"tag-optional": "\"\""
									}
								},
								{
									"id": "tween-two-properties",
									"objectClass": "12a",
									"sid": 886185767176513,
									"behaviorType": "Tween",
									"parameters": {
										"tags": "\"\"",
										"property": "size",
										"end-x": "Self.AyatX+50",
										"end-y": "Self.AyatY+50",
										"time": "0.2",
										"ease": "default",
										"destroy-on-complete": "no",
										"loop": "no",
										"ping-pong": "no",
										"repeat-count": "1"
									}
								},
								{
									"id": "set-animation-frame",
									"objectClass": "12a",
									"sid": 727549120282740,
									"parameters": {
										"frame-number": "25"
									}
								},
								{
									"id": "wait",
									"objectClass": "System",
									"sid": 598868350619831,
									"parameters": {
										"seconds": "7"
									}
								},
								{
									"id": "set-animation-frame",
									"objectClass": "12a",
									"sid": 380524521068436,
									"parameters": {
										"frame-number": "10"
									}
								},
								{
									"id": "tween-two-properties",
									"objectClass": "12a",
									"sid": 652567787009319,
									"behaviorType": "Tween",
									"parameters": {
										"tags": "\"\"",
										"property": "size",
										"end-x": "Self.AyatX",
										"end-y": "Self.AyatY",
										"time": "0.2",
										"ease": "easeinback",
										"destroy-on-complete": "no",
										"loop": "no",
										"ping-pong": "no",
										"repeat-count": "1"
									}
								}
							],
							"sid": 961845556963378
						},
						{
							"eventType": "block",
							"conditions": [
								{
									"id": "compare-eventvar",
									"objectClass": "System",
									"sid": 769791878707077,
									"parameters": {
										"variable": "Iqro12",
										"comparison": 0,
										"value": "11"
									}
								},
								{
									"id": "compare-animation-frame",
									"objectClass": "12a",
									"sid": 570227795709350,
									"parameters": {
										"comparison": 0,
										"number": "11"
									}
								}
							],
							"actions": [
								{
									"id": "stop-all",
									"objectClass": "Audio",
									"sid": 529901780388766
								},
								{
									"id": "play",
									"objectClass": "Audio",
									"sid": 343993054906363,
									"parameters": {
										"audio-file": "11L",
										"loop": "not-looping",
										"volume": "0",
										"stereo-pan": "0",
										"tag-optional": "\"\""
									}
								},
								{
									"id": "tween-two-properties",
									"objectClass": "12a",
									"sid": 822083641819314,
									"behaviorType": "Tween",
									"parameters": {
										"tags": "\"\"",
										"property": "size",
										"end-x": "Self.AyatX+50",
										"end-y": "Self.AyatY+50",
										"time": "0.2",
										"ease": "default",
										"destroy-on-complete": "no",
										"loop": "no",
										"ping-pong": "no",
										"repeat-count": "1"
									}
								},
								{
									"id": "set-animation-frame",
									"objectClass": "12a",
									"sid": 107515365540715,
									"parameters": {
										"frame-number": "26"
									}
								},
								{
									"id": "wait",
									"objectClass": "System",
									"sid": 439663754207617,
									"parameters": {
										"seconds": "7"
									}
								},
								{
									"id": "set-animation-frame",
									"objectClass": "12a",
									"sid": 400312115358719,
									"parameters": {
										"frame-number": "11"
									}
								},
								{
									"id": "tween-two-properties",
									"objectClass": "12a",
									"sid": 875613157430622,
									"behaviorType": "Tween",
									"parameters": {
										"tags": "\"\"",
										"property": "size",
										"end-x": "Self.AyatX",
										"end-y": "Self.AyatY",
										"time": "0.2",
										"ease": "easeinback",
										"destroy-on-complete": "no",
										"loop": "no",
										"ping-pong": "no",
										"repeat-count": "1"
									}
								}
							],
							"sid": 916215445115530
						},
						{
							"eventType": "block",
							"conditions": [
								{
									"id": "compare-eventvar",
									"objectClass": "System",
									"sid": 757665318257806,
									"parameters": {
										"variable": "Iqro12",
										"comparison": 0,
										"value": "12"
									}
								},
								{
									"id": "compare-animation-frame",
									"objectClass": "12a",
									"sid": 746755333222156,
									"parameters": {
										"comparison": 0,
										"number": "12"
									}
								}
							],
							"actions": [
								{
									"id": "stop-all",
									"objectClass": "Audio",
									"sid": 821461350935528
								},
								{
									"id": "play",
									"objectClass": "Audio",
									"sid": 829294603058106,
									"parameters": {
										"audio-file": "12L",
										"loop": "not-looping",
										"volume": "0",
										"stereo-pan": "0",
										"tag-optional": "\"\""
									}
								},
								{
									"id": "tween-two-properties",
									"objectClass": "12a",
									"sid": 426937550470444,
									"behaviorType": "Tween",
									"parameters": {
										"tags": "\"\"",
										"property": "size",
										"end-x": "Self.AyatX+50",
										"end-y": "Self.AyatY+50",
										"time": "0.2",
										"ease": "default",
										"destroy-on-complete": "no",
										"loop": "no",
										"ping-pong": "no",
										"repeat-count": "1"
									}
								},
								{
									"id": "set-animation-frame",
									"objectClass": "12a",
									"sid": 750039784323496,
									"parameters": {
										"frame-number": "27"
									}
								},
								{
									"id": "wait",
									"objectClass": "System",
									"sid": 879696992371806,
									"parameters": {
										"seconds": "7"
									}
								},
								{
									"id": "set-animation-frame",
									"objectClass": "12a",
									"sid": 910920158832003,
									"parameters": {
										"frame-number": "12"
									}
								},
								{
									"id": "tween-two-properties",
									"objectClass": "12a",
									"sid": 729893443290469,
									"behaviorType": "Tween",
									"parameters": {
										"tags": "\"\"",
										"property": "size",
										"end-x": "Self.AyatX",
										"end-y": "Self.AyatY",
										"time": "0.2",
										"ease": "easeinback",
										"destroy-on-complete": "no",
										"loop": "no",
										"ping-pong": "no",
										"repeat-count": "1"
									}
								}
							],
							"sid": 188037690933357
						},
						{
							"eventType": "block",
							"conditions": [
								{
									"id": "compare-eventvar",
									"objectClass": "System",
									"sid": 597264904837015,
									"parameters": {
										"variable": "Iqro12",
										"comparison": 0,
										"value": "13"
									}
								},
								{
									"id": "compare-animation-frame",
									"objectClass": "12a",
									"sid": 729915447641201,
									"parameters": {
										"comparison": 0,
										"number": "13"
									}
								}
							],
							"actions": [
								{
									"id": "stop-all",
									"objectClass": "Audio",
									"sid": 926738184665478
								},
								{
									"id": "play",
									"objectClass": "Audio",
									"sid": 956786735539112,
									"parameters": {
										"audio-file": "13L",
										"loop": "not-looping",
										"volume": "0",
										"stereo-pan": "0",
										"tag-optional": "\"\""
									}
								},
								{
									"id": "tween-two-properties",
									"objectClass": "12a",
									"sid": 784957003385600,
									"behaviorType": "Tween",
									"parameters": {
										"tags": "\"\"",
										"property": "size",
										"end-x": "Self.AyatX+50",
										"end-y": "Self.AyatY+50",
										"time": "0.2",
										"ease": "default",
										"destroy-on-complete": "no",
										"loop": "no",
										"ping-pong": "no",
										"repeat-count": "1"
									}
								},
								{
									"id": "set-animation-frame",
									"objectClass": "12a",
									"sid": 811120965741856,
									"parameters": {
										"frame-number": "28"
									}
								},
								{
									"id": "wait",
									"objectClass": "System",
									"sid": 558746937410239,
									"parameters": {
										"seconds": "7"
									}
								},
								{
									"id": "set-animation-frame",
									"objectClass": "12a",
									"sid": 407534022315332,
									"parameters": {
										"frame-number": "13"
									}
								},
								{
									"id": "tween-two-properties",
									"objectClass": "12a",
									"sid": 470207820306152,
									"behaviorType": "Tween",
									"parameters": {
										"tags": "\"\"",
										"property": "size",
										"end-x": "Self.AyatX",
										"end-y": "Self.AyatY",
										"time": "0.2",
										"ease": "easeinback",
										"destroy-on-complete": "no",
										"loop": "no",
										"ping-pong": "no",
										"repeat-count": "1"
									}
								}
							],
							"sid": 155649145441398
						},
						{
							"eventType": "block",
							"conditions": [
								{
									"id": "compare-eventvar",
									"objectClass": "System",
									"sid": 931546864947833,
									"parameters": {
										"variable": "Iqro12",
										"comparison": 0,
										"value": "14"
									}
								},
								{
									"id": "compare-animation-frame",
									"objectClass": "12a",
									"sid": 613281671837168,
									"parameters": {
										"comparison": 0,
										"number": "14"
									}
								}
							],
							"actions": [
								{
									"id": "stop-all",
									"objectClass": "Audio",
									"sid": 901731145071823
								},
								{
									"id": "play",
									"objectClass": "Audio",
									"sid": 455393399448755,
									"parameters": {
										"audio-file": "14L",
										"loop": "not-looping",
										"volume": "0",
										"stereo-pan": "0",
										"tag-optional": "\"\""
									}
								},
								{
									"id": "tween-two-properties",
									"objectClass": "12a",
									"sid": 680409876167262,
									"behaviorType": "Tween",
									"parameters": {
										"tags": "\"\"",
										"property": "size",
										"end-x": "Self.AyatX+50",
										"end-y": "Self.AyatY+50",
										"time": "0.2",
										"ease": "default",
										"destroy-on-complete": "no",
										"loop": "no",
										"ping-pong": "no",
										"repeat-count": "1"
									}
								},
								{
									"id": "set-animation-frame",
									"objectClass": "12a",
									"sid": 732302114775839,
									"parameters": {
										"frame-number": "29"
									}
								},
								{
									"id": "wait",
									"objectClass": "System",
									"sid": 880464113503178,
									"parameters": {
										"seconds": "7"
									}
								},
								{
									"id": "set-animation-frame",
									"objectClass": "12a",
									"sid": 131111564575189,
									"parameters": {
										"frame-number": "14"
									}
								},
								{
									"id": "tween-two-properties",
									"objectClass": "12a",
									"sid": 912902138358634,
									"behaviorType": "Tween",
									"parameters": {
										"tags": "\"\"",
										"property": "size",
										"end-x": "Self.AyatX",
										"end-y": "Self.AyatY",
										"time": "0.2",
										"ease": "easeinback",
										"destroy-on-complete": "no",
										"loop": "no",
										"ping-pong": "no",
										"repeat-count": "1"
									}
								}
							],
							"sid": 544993928043581
						}
					]
				},
				{
					"eventType": "block",
					"conditions": [
						{
							"id": "on-touched-object",
							"objectClass": "Touch",
							"sid": 603969444538219,
							"parameters": {
								"object": "12a",
								"type": "start"
							}
						}
					],
					"actions": [
						{
							"id": "set-eventvar-value",
							"objectClass": "System",
							"sid": 403141185040310,
							"parameters": {
								"variable": "Iqro12",
								"value": "12a.AnimationFrame"
							}
						},
						{
							"callFunction": "Iqro12",
							"sid": 263941991004829
						}
					],
					"sid": 413356440689838
				}
			],
			"sid": 112572842596795
		}
	],
	"sid": 645093727208422
}